mcp_policy_test/__init__.py
mcp_policy_test/server.py
mcp_policy_test-0.1.1.dist-info/WHEEL
mcp_policy_test-0.1.1.dist-info/entry_points.txt
mcp_policy_test-0.1.1.dist-info/METADATA
mcp_policy_test-0.1.1.dist-info/RECORD
